easetools/__init__.py
easetools/module1.py
easetools-0.2.dist-info/METADATA
easetools-0.2.dist-info/WHEEL
easetools-0.2.dist-info/top_level.txt
easetools-0.2.dist-info/RECORD
