Metadata-Version: 2.1
Name: easetools
Version: 0.2
Summary: number theory, and matrix operations. The package is designed to simplify calculations for common use cases, including arithmetic, statistical analysis, combinatorics, and linear algebra. 
Home-page: https://github.com/MaruthiCharan2403/easetools
Author: Y S S M Charan
Author-email: yssmc24@gmail.com
Classifier: Programming Language :: Python :: 3
Classifier: License :: OSI Approved :: MIT License
Classifier: Operating System :: OS Independent
Requires-Python: >=3.6
